app_store_asset_cli/__init__.py
app_store_asset_cli/assets.py
app_store_asset_cli/config.py
app_store_asset_cli/download_app_assets.py
app_store_asset_cli/locale_utils.py
app_store_asset_cli/main.py
app_store_asset_cli/output.py
app_store_asset_cli/validation.py
app_store_asset_cli-0.1.2.dist-info/licenses/LICENSE
app_store_asset_cli-0.1.2.dist-info/METADATA
app_store_asset_cli-0.1.2.dist-info/WHEEL
app_store_asset_cli-0.1.2.dist-info/entry_points.txt
app_store_asset_cli-0.1.2.dist-info/top_level.txt
app_store_asset_cli-0.1.2.dist-info/RECORD
