Metadata-Version: 2.4
Name: app-store-asset-cli
Version: 0.1.2
Summary: Download App Store logos and screenshots
Author: Your Name
License: MIT
Classifier: Development Status :: 3 - Alpha
Classifier: Intended Audience :: Developers
Classifier: License :: OSI Approved :: MIT License
Classifier: Programming Language :: Python :: 3
Classifier: Programming Language :: Python :: 3.8
Classifier: Programming Language :: Python :: 3.9
Classifier: Programming Language :: Python :: 3.10
Classifier: Programming Language :: Python :: 3.11
Requires-Python: >=3.8
License-File: LICENSE
Requires-Dist: crawl4ai>=0.7.0
Requires-Dist: aiohttp>=3.8.0
Requires-Dist: beautifulsoup4>=4.12.0
Requires-Dist: python-dotenv>=1.0.0
Requires-Dist: reportlab>=4.0.0
Requires-Dist: Pillow>=10.0.0
Requires-Dist: typer>=0.9.0
Requires-Dist: rich>=13.0.0
Dynamic: author
Dynamic: classifier
Dynamic: description
Dynamic: description-content-type
Dynamic: license
Dynamic: license-file
Dynamic: requires-dist
Dynamic: requires-python
Dynamic: summary
